mms_lid/__init__.py
mms_lid/cli.py
mms_lid/config.py
mms_lid/decoder.py
mms_lid/model.py
mms_lid/pipeline.py
mms_lid-0.1.2.dist-info/METADATA
mms_lid-0.1.2.dist-info/WHEEL
mms_lid-0.1.2.dist-info/entry_points.txt
mms_lid-0.1.2.dist-info/top_level.txt
mms_lid-0.1.2.dist-info/RECORD
