Metadata-Version: 2.4
Name: mms-lid
Version: 0.1.2
Summary: A Robust Language Identification Tool using MMS-1B
Home-page: https://huggingface.co/N01N9/mms-1b-ll-lid-timestamp
Author: N01N9
Classifier: Programming Language :: Python :: 3
Classifier: License :: OSI Approved :: MIT License
Classifier: Operating System :: OS Independent
Requires-Python: >=3.8
Requires-Dist: torch>=2.0.0
Requires-Dist: torchaudio>=2.0.0
Requires-Dist: transformers>=4.30.0
Requires-Dist: numpy
Requires-Dist: scipy
Requires-Dist: tqdm
Requires-Dist: requests
Dynamic: author
Dynamic: classifier
Dynamic: description
Dynamic: description-content-type
Dynamic: home-page
Dynamic: requires-dist
Dynamic: requires-python
Dynamic: summary
